AUTHORS.rst
CONTRIBUTING.rst
HISTORY.rst
LICENSE
MANIFEST.in
README.rst
setup.cfg
setup.py
docs/authors.rst
docs/conf.py
docs/contributing.rst
docs/history.rst
docs/index.rst
docs/installation.rst
docs/readme.rst
docs/usage.rst
popart/__init__.py
popart/popart.py
popart.egg-info/PKG-INFO
popart.egg-info/SOURCES.txt
popart.egg-info/dependency_links.txt
popart.egg-info/not-zip-safe
popart.egg-info/top_level.txt
tests/test_popart.py