Metadata-Version: 1.1
Name: popart
Version: 0.1.1
Summary: Population based training for Pytorch models.
Home-page: https://github.com/yngtodd/popart
Author: Todd Young
Author-email: youngmt1@ornl.gov
License: BSD license
Keywords: popart
Platform: UNKNOWN
Classifier: Development Status :: 2 - Pre-Alpha
Classifier: Intended Audience :: Developers
Classifier: License :: OSI Approved :: BSD License
Classifier: Natural Language :: English
Classifier: Programming Language :: Python :: 2
Classifier: Programming Language :: Python :: 2.7
Classifier: Programming Language :: Python :: 3
Classifier: Programming Language :: Python :: 3.4
Classifier: Programming Language :: Python :: 3.5
Classifier: Programming Language :: Python :: 3.6
Classifier: Programming Language :: Python :: 3.7
